ansiparser/__init__.py
ansiparser/api.py
ansiparser/converter.py
ansiparser/re_pattern.py
ansiparser/screen_parser.py
ansiparser/sequence_parser.py
ansiparser/sequence_utils.py
ansiparser/structures.py
ansiparser/utils.py
ansiparser-1.3.2.dist-info/LICENSE
ansiparser-1.3.2.dist-info/METADATA
ansiparser-1.3.2.dist-info/WHEEL
ansiparser-1.3.2.dist-info/RECORD
