Metadata-Version: 2.1
Name: ansiparser
Version: 1.3.2
Summary: A convenient library for converting ANSI escape sequences into text or HTML.
Home-page: https://github.com/bubble-tea-project/ansiparser
License: Apache-2.0
Author: vHrqO
Author-email: you@example.com
Requires-Python: >=3.10,<4.0
Classifier: License :: OSI Approved :: Apache Software License
Classifier: Programming Language :: Python :: 3
Classifier: Programming Language :: Python :: 3.10
Classifier: Programming Language :: Python :: 3.11
Classifier: Programming Language :: Python :: 3.12
Classifier: Programming Language :: Python :: 3.13
Requires-Dist: beautifulsoup4 (>=4.12.3,<5.0.0)
Project-URL: Repository, https://github.com/bubble-tea-project/ansiparser
